rule4ml/__init__.py
rule4ml/_version.py
rule4ml/models/__init__.py
rule4ml/models/estimators.py
rule4ml/models/metrics.py
rule4ml/models/tuning.py
rule4ml/models/weights/BRAM_MLP.weights.h5
rule4ml/models/weights/BRAM_MLP_config.json
rule4ml/models/weights/CYCLES_MLP.weights.h5
rule4ml/models/weights/CYCLES_MLP_config.json
rule4ml/models/weights/DSP_MLP.weights.h5
rule4ml/models/weights/DSP_MLP_config.json
rule4ml/models/weights/FF_MLP.weights.h5
rule4ml/models/weights/FF_MLP_config.json
rule4ml/models/weights/LUT_MLP.weights.h5
rule4ml/models/weights/LUT_MLP_config.json
rule4ml/models/weights/__init__.py
rule4ml/parsers/__init__.py
rule4ml/parsers/data_parser.py
rule4ml/parsers/network_parser.py
rule4ml/parsers/supported_boards.json
rule4ml/parsers/utils.py
rule4ml_test-0.1.8.dist-info/LICENSE
rule4ml_test-0.1.8.dist-info/METADATA
rule4ml_test-0.1.8.dist-info/WHEEL
rule4ml_test-0.1.8.dist-info/top_level.txt
rule4ml_test-0.1.8.dist-info/RECORD
