Metadata-Version: 2.1
Name: rule4ml-test
Version: 0.1.8
Summary: Resource utilization and Latency Estimation for ML on FPGA
Author: IMPETUS Team
Author-email: impetus@usherbrooke.ca
License: GPL-3.0
Classifier: Development Status :: 4 - Beta
Classifier: Intended Audience :: Developers
Classifier: Intended Audience :: Science/Research
Classifier: License :: OSI Approved :: GNU General Public License v3 (GPLv3)
Classifier: Programming Language :: Python :: 3
Classifier: Programming Language :: Python :: 3 :: Only
Classifier: Topic :: Software Development :: Libraries
Classifier: Topic :: Software Development :: Libraries :: Python Modules
Requires-Python: >=3.9
License-File: LICENSE
Requires-Dist: pandas
Requires-Dist: scikit-learn
Requires-Dist: tensorflow
Requires-Dist: keras
Requires-Dist: keras-tuner
Provides-Extra: dev
Requires-Dist: pre-commit ; extra == 'dev'
Requires-Dist: pytest ; extra == 'dev'
Requires-Dist: torch ; extra == 'dev'
Requires-Dist: onnx ; extra == 'dev'
